flickr_api_pkg/__init__.py
flickr_api_pkg/mirror_flickr.py
flickr_package-1.0.0.dist-info/LICENSE
flickr_package-1.0.0.dist-info/METADATA
flickr_package-1.0.0.dist-info/WHEEL
flickr_package-1.0.0.dist-info/top_level.txt
flickr_package-1.0.0.dist-info/RECORD
