Metadata-Version: 2.1
Name: flickr-package
Version: 1.0.0
Summary: flickr_package use to batch download photos from user Flickr
Home-page: https://github.com/intek-training-jsc/flickr-mirroring-KV16
Author: Khoi Vo
Author-email: khoi.vo@f4.intek.edu.vn
License: UNKNOWN
Platform: UNKNOWN
Classifier: Programming Language :: Python :: 3
Classifier: License :: OSI Approved :: MIT License
Requires-Python: >=3.6
Requires-Dist: bleach (==3.1.5)
Requires-Dist: certifi (==2020.4.5.1)
Requires-Dist: cffi (==1.14.0)
Requires-Dist: chardet (==3.0.4)
Requires-Dist: cryptography (==2.9.2)
Requires-Dist: docutils (==0.16)
Requires-Dist: idna (==2.9)
Requires-Dist: keyring (==21.2.1)
Requires-Dist: langdetect (==1.0.8)
Requires-Dist: packaging (==20.3)
Requires-Dist: pkginfo (==1.5.0.1)
Requires-Dist: pycountry (==19.8.18)
Requires-Dist: pycparser (==2.20)
Requires-Dist: pygments (==2.6.1)
Requires-Dist: pyparsing (==2.4.7)
Requires-Dist: readme-renderer (==26.0)
Requires-Dist: requests (==2.23.0)
Requires-Dist: requests-toolbelt (==0.9.1)
Requires-Dist: six (==1.14.0)
Requires-Dist: tqdm (==4.46.0)
Requires-Dist: twine (==3.1.1)
Requires-Dist: urllib3 (==1.25.9)
Requires-Dist: webencodings (==0.5.1)
Requires-Dist: wheel (==0.34.2)
Requires-Dist: zipp (==3.1.0)
Requires-Dist: importlib-metadata (==1.6.0) ; python_version < "3.8"
Requires-Dist: jeepney (==0.4.3) ; sys_platform == "linux"
Requires-Dist: secretstorage (==3.1.2) ; sys_platform == "linux"
Provides-Extra: dev
Requires-Dist: appdirs (==1.4.3) ; extra == 'dev'
Requires-Dist: attrs (==19.3.0) ; extra == 'dev'
Requires-Dist: cached-property (==1.5.1) ; extra == 'dev'
Requires-Dist: cerberus (==1.3.2) ; extra == 'dev'
Requires-Dist: certifi (==2020.4.5.1) ; extra == 'dev'
Requires-Dist: chardet (==3.0.4) ; extra == 'dev'
Requires-Dist: click (==7.1.2) ; extra == 'dev'
Requires-Dist: colorama (==0.4.3) ; extra == 'dev'
Requires-Dist: distlib (==0.3.0) ; extra == 'dev'
Requires-Dist: idna (==2.9) ; extra == 'dev'
Requires-Dist: orderedmultidict (==1.0.1) ; extra == 'dev'
Requires-Dist: packaging (==20.3) ; extra == 'dev'
Requires-Dist: pathspec (==0.8.0) ; extra == 'dev'
Requires-Dist: pep517 (==0.8.2) ; extra == 'dev'
Requires-Dist: pip-shims (==0.5.2) ; extra == 'dev'
Requires-Dist: pipenv-setup (==3.0.1) ; extra == 'dev'
Requires-Dist: pipfile (==0.0.2) ; extra == 'dev'
Requires-Dist: plette[validation] (==0.2.3) ; extra == 'dev'
Requires-Dist: pyparsing (==2.4.7) ; extra == 'dev'
Requires-Dist: python-dateutil (==2.8.1) ; extra == 'dev'
Requires-Dist: regex (==2020.5.7) ; extra == 'dev'
Requires-Dist: requests (==2.23.0) ; extra == 'dev'
Requires-Dist: requirementslib (==1.5.7) ; extra == 'dev'
Requires-Dist: six (==1.14.0) ; extra == 'dev'
Requires-Dist: toml (==0.10.0) ; extra == 'dev'
Requires-Dist: tomlkit (==0.6.0) ; extra == 'dev'
Requires-Dist: typed-ast (==1.4.1) ; extra == 'dev'
Requires-Dist: typing (==3.7.4.1) ; extra == 'dev'
Requires-Dist: urllib3 (==1.25.9) ; extra == 'dev'
Requires-Dist: vistir (==0.5.0) ; extra == 'dev'
Requires-Dist: wheel (==0.34.2) ; extra == 'dev'
Requires-Dist: zipp (==3.1.0) ; extra == 'dev'
Requires-Dist: importlib-metadata (==1.6.0) ; (python_version < "3.8") and extra == 'dev'
Requires-Dist: black (==19.10b0) ; (python_version >= "3.6") and extra == 'dev'
